asmac.py
MacSwitch-0.1.9.dist-info/METADATA
MacSwitch-0.1.9.dist-info/WHEEL
MacSwitch-0.1.9.dist-info/entry_points.txt
MacSwitch-0.1.9.dist-info/top_level.txt
MacSwitch-0.1.9.dist-info/RECORD
