Metadata-Version: 2.1
Name: MacSwitch
Version: 0.1.9
Summary: Remote Antenna Switch
Home-page: https://github.com/0x9900/AntennaSwitch/
Author: Fred C. (W6BSD)
Author-email: w6bsd@bsdworld.org
License: BSD
Classifier: Development Status :: 5 - Production/Stable
Classifier: Intended Audience :: Developers
Classifier: License :: OSI Approved :: BSD License
Classifier: Operating System :: OS Independent
Classifier: Environment :: X11 Applications :: Qt
Classifier: Programming Language :: Python
Classifier: Programming Language :: Python :: 3
Classifier: Programming Language :: Python :: 3.8
Classifier: Programming Language :: Python :: 3.9
Classifier: Programming Language :: Python :: 3.10
Classifier: Topic :: Communications :: Ham Radio
Requires-Dist: PyQt5
Requires-Dist: requests
